svdata-0.0.16.dist-info/METADATA
svdata-0.0.16.dist-info/WHEEL
svdata-0.0.16.dist-info/licenses/LICENSE
svdata/__init__.py
svdata/__init__.pyi
svdata/py.typed
svdata/svdata.cpython-310-i386-linux-gnu.so
svdata-0.0.16.dist-info/RECORD
