Metadata-Version: 2.3
Name: svdata
Version: 0.0.16
Classifier: Programming Language :: Rust
Classifier: Programming Language :: Python :: Implementation :: CPython
Classifier: Programming Language :: Python :: Implementation :: PyPy
Classifier: Programming Language :: Python :: 3.8
Classifier: Programming Language :: Python :: 3.9
Classifier: Programming Language :: Python :: 3.10
Classifier: Programming Language :: Python :: 3.11
Classifier: Programming Language :: Python :: 3.12
Classifier: License :: OSI Approved :: MIT License
Classifier: Development Status :: 3 - Alpha
Requires-Dist: mypy ; extra == 'dev'
Requires-Dist: ruff ; extra == 'dev'
Requires-Dist: pytest ; extra == 'dev'
Requires-Dist: mkdocstrings ; extra == 'dev'
Provides-Extra: dev
License-File: LICENSE
Summary: Parse systemverilog files in Python.
Keywords: systemverilog,parser,python
Author-email: Pontus Thomsson <pontusthomsson@gmail.com>
Maintainer-email: Pontus Thomsson <pontusthomsson@gmail.com>
Requires-Python: >=3.8
Project-URL: Homepage, https://github.com/prokie/svdata
Project-URL: Documentation, https://github.com/prokie/svdata
Project-URL: Repository, https://github.com/prokie/svdata
Project-URL: Issues, https://github.com/prokie/svdata/issues
